degapm_uart/__init__.py
degapm_uart/degapm_uart.py
degapm_uart-1.0.0.dist-info/LICENSE
degapm_uart-1.0.0.dist-info/METADATA
degapm_uart-1.0.0.dist-info/WHEEL
degapm_uart-1.0.0.dist-info/top_level.txt
degapm_uart-1.0.0.dist-info/RECORD
